Metadata-Version: 1.0
Name: aqua-python
Version: 1.3
Summary: A simple formatter for Python code that adheres to the PEP8 standards
Home-page: UNKNOWN
Author: Alexander J. Zerphy
Author-email: ajz5109@psu.edu
License: GPL-3.0
Platform: UNKNOWN
